kb_mlx/__init__.py
kb_mlx/app.py
kb_mlx/cli.py
kb_mlx-0.3.1.dist-info/licenses/LICENSE
kb_mlx-0.3.1.dist-info/METADATA
kb_mlx-0.3.1.dist-info/WHEEL
kb_mlx-0.3.1.dist-info/entry_points.txt
kb_mlx-0.3.1.dist-info/top_level.txt
kb_mlx-0.3.1.dist-info/RECORD
