Metadata-Version: 2.4
Name: kb-mlx
Version: 0.3.1
Summary: Voice Blender CLI for Kokoro MLX
Author: Thomas Schmidt
License: MIT
Project-URL: Homepage, https://github.com/tsmdt/kokoro-blender-MLX
Classifier: Programming Language :: Python :: 3
Classifier: License :: OSI Approved :: MIT License
Classifier: Operating System :: OS Independent
Requires-Python: >=3.11
License-File: LICENSE
Requires-Dist: click==8.1.8
Requires-Dist: typer==0.15.1
Requires-Dist: mlx==0.29.0
Requires-Dist: mlx-audio==0.2.5
Requires-Dist: kokoro==0.9.4
Requires-Dist: gradio==5.31.0
Dynamic: license-file
